tracwikiimporter/__init__.py
tracwikiimporter/importer.py
tracwikiimporter/scripts/__init__.py
tracwikiimporter/scripts/wiki_from_trac/__init__.py
tracwikiimporter/scripts/wiki_from_trac/extractors.py
tracwikiimporter/scripts/wiki_from_trac/loaders.py
tracwikiimporter/scripts/wiki_from_trac/wiki_from_trac.py
tracwikiimporter/templates/index.html
tracwikiimporter/tests/__init__.py
tracwikiimporter/tests/test_importer.py
TracWikiImporter-0.5.1.dist-info/COPYING
TracWikiImporter-0.5.1.dist-info/METADATA
TracWikiImporter-0.5.1.dist-info/WHEEL
TracWikiImporter-0.5.1.dist-info/entry_points.txt
TracWikiImporter-0.5.1.dist-info/top_level.txt
TracWikiImporter-0.5.1.dist-info/zip-safe
TracWikiImporter-0.5.1.dist-info/RECORD
